mdformat_pelican/__init__.py
mdformat_pelican/plugin.py
mdformat_pelican-0.2.2.dist-info/entry_points.txt
mdformat_pelican-0.2.2.dist-info/licenses/LICENSE
mdformat_pelican-0.2.2.dist-info/WHEEL
mdformat_pelican-0.2.2.dist-info/METADATA
mdformat_pelican-0.2.2.dist-info/RECORD
