Metadata-Version: 2.4
Name: mdformat_pelican
Version: 0.2.2
Summary: An mdformat plugin for pelican markdown items
Home-page: https://github.com/gaige/mdformat-pelican
Keywords: mdformat,markdown,markdown-it
Author: Gaige B. Paulsen
Author-email: gaige@cluetrust.com
Requires-Python: >=3.6
Classifier: Intended Audience :: Developers
Classifier: License :: OSI Approved :: MIT License
Classifier: Programming Language :: Python :: 3
Classifier: Topic :: Software Development :: Libraries :: Python Modules
License-File: LICENSE
Requires-Dist: mdformat >=0.7.0,<0.8.0
Requires-Dist: pre-commit ; extra == "dev"
Requires-Dist: pytest~=6.0 ; extra == "test"
Requires-Dist: coverage ; extra == "test"
Requires-Dist: pytest-cov ; extra == "test"
Provides-Extra: dev
Provides-Extra: test
